{
  "tit": "Returns",
  "eh": "F",
  "sl": "",
  "proj": "FARMERPPM",
  "pid": "16",
  "idt": "returns_rpt",
  "rh1": "Returns",
  "rh2": null,
  "rf1": null,
  "rf2": null,
  "roc": "10",
  "ih": "F",
  "exd_tb": "True",
  "fd_to_dp": "docdt,description,cropage",
  "sc_in_rpt": "True",
  "rt": "onlinereport",
  "lp": "10",
  "stl": "F",
  "dorf": null,
  "rep_des": "{\"comp\": [{\"type\": \"text\",\"name\": \"\",\"id\": \"\"},{\"type\": \"select\",\"name\": \"\",\"id\": \"\"}],\"condition\":[]}",
  "reportfield_meta": [
    {
      "sl": "docno",
      "re": "Returns",
      "quy": "Return",
      "cap": "Doc Number",
      "nod": "0",
      "srt": "F",
      "sht": "F",
      "ih": "F",
      "ac": "F",
      "dor": "F",
      "ca": "left",
      "dz": "F",
      "dio": "1",
      "wd": "0",
      "het": "0",
      "data_typ": "char",
      "icls": null,
      "fielddesc": "",
      "exp": "",
      "vexp": "",
      "shm": "F"
    },
    {
      "sl": "docdt",
      "re": "Returns",
      "quy": "Return",
      "cap": "Doc Date",
      "nod": "0",
      "srt": "F",
      "sht": "F",
      "ih": "F",
      "ac": "F",
      "dor": "F",
      "ca": "left",
      "dz": "F",
      "dio": "2",
      "wd": "0",
      "het": "0",
      "data_typ": "datetime",
      "icls": null,
      "fielddesc": "",
      "exp": "",
      "vexp": "",
      "shm": "F"
    },
    {
      "sl": "description",
      "re": "Returns",
      "quy": "Return",
      "cap": "Description",
      "nod": "0",
      "srt": "F",
      "sht": "F",
      "ih": "F",
      "ac": "F",
      "dor": "F",
      "ca": "left",
      "dz": "F",
      "dio": "3",
      "wd": "0",
      "het": "0",
      "data_typ": "char",
      "icls": null,
      "fielddesc": "",
      "exp": "",
      "vexp": "",
      "shm": "F"
    },
    {
      "sl": "qty",
      "re": "Returns",
      "quy": "Return",
      "cap": "Qty",
      "nod": "1",
      "srt": "F",
      "sht": "T",
      "ih": "F",
      "ac": "F",
      "dor": "F",
      "ca": "left",
      "dz": "F",
      "dio": "4",
      "wd": "0",
      "het": "0",
      "data_typ": "numeric",
      "icls": null,
      "fielddesc": "",
      "exp": "",
      "vexp": "",
      "shm": "F"
    },
    {
      "sl": "totamt",
      "re": "Returns",
      "quy": "Return",
      "cap": "Total Amt",
      "nod": "2",
      "srt": "F",
      "sht": "T",
      "ih": "F",
      "ac": "F",
      "dor": "F",
      "ca": "left",
      "dz": "F",
      "dio": "5",
      "wd": "0",
      "het": "0",
      "data_typ": "numeric",
      "icls": null,
      "fielddesc": "",
      "exp": "",
      "vexp": "",
      "shm": "F"
    },
    {
      "sl": "cropage",
      "re": "Returns",
      "quy": "Return",
      "cap": "Crop Age",
      "nod": "0",
      "srt": "F",
      "sht": "F",
      "ih": "F",
      "ac": "F",
      "dor": "F",
      "ca": "left",
      "dz": "F",
      "dio": "6",
      "wd": "0",
      "het": "0",
      "data_typ": "numeric",
      "icls": null,
      "fielddesc": "",
      "exp": "",
      "vexp": "",
      "shm": "F"
    }
  ],
  "reportparamfield_meta": [
    {
      "sl": "ragid",
      "idt": "ragid",
      "cap": "Ragid",
      "rep": "returns_rpt",
      "quy": "Return",
      "do": "2",
      "ih": "False",
      "nod": "0",
      "vf": null,
      "df": null,
      "ae": "F",
      "exp": "",
      "ep": "",
      "ve": "",
      "vep": "",
      "comp": "charfield",
      "wt": "text",
      "data_typ": "char",
      "sql": "",
      "dbtype": null,
      "isdep": "False",
      "cf": "False"
    }
  ],
  "query_meta": [
    {
      "tit": "Return",
      "rep": "Returns",
      "sq": "SELECT a.cirno AS docno, a.cirdt AS \t\t\r\ndocdt, im.itemid AS description,  b.qty AS qty, b.amount AS totamt, a.cropage\t\t\r\nFROM cir1 a, cir2 b, itemmaster im, igdetail ig, cropcycle c\t\t\r\nWHERE a.cir1id=b.cir1id AND b.itemid = im.itemmasterid AND im.subgroup = ig.igdetailid \r\nAND a.cropcycleid = c.cropcycleid AND c.ragid  = :ragid\r\nORDER BY docdt,docno",
      "imq": "T",
      "jot": "none",
      "isq": "F"
    }
  ],
  "repgrouping_meta": [],
  "repaction_meta": [
    {
      "at": "paramFab",
      "ReportPrintFormatAction": "",
      "ReportPDF": "",
      "ReportCSV": "",
      "ReportHTML": "",
      "ReportSubmit": "",
      "Payconfig": "",
      "NewActionConfig": "",
      "paramFab": {
        "tit": "paramFab",
        "icls": "construct",
        "re": "Returns"
      }
    }
  ],
  "repfieldbutexp_meta": [],
  "tem_type": null,
  "template": "",
  "dis_btn_len": null,
  "dis_btn_pos": null,
  "xcoord": null,
  "ycoord": null,
  "sxy": "False",
  "gtype": null,
  "init_load": "False",
  "scan_report": "None",
  "email_config": null,
  "sms_config": null,
  "dasb_rpt": "F"
}